grabgpu/__init__.py
grabgpu/get_idle.py
grabgpu/gpuinfo.py
grabgpu-0.1.5.dist-info/METADATA
grabgpu-0.1.5.dist-info/WHEEL
grabgpu-0.1.5.dist-info/top_level.txt
grabgpu-0.1.5.dist-info/RECORD
